{
   "decameron":[
      {
         "proem":{
            "narrator":"author"
         }
      },
      {
         "days":[
            {
               "1":{
                  "leader":"pampinea",
                  "sections":[
                     {
                        "introduction":{
                           "narrator":"author"
                        }
                     },
                     {
                        "1":{
                           "narrator":"panfilo"
                        }
                     },
                     {
                        "2":{
                           "narrator":"neifile"
                        }
                     },
                     {
                        "3":{
                           "narrator":"filomena"
                        }
                     },
                     {
                        "4":{
                           "narrator":"dioneo"
                        }
                     },
                     {
                        "5":{
                           "narrator":"fiammetta"
                        }
                     },
                     {
                        "6":{
                           "narrator":"emilia"
                        }
                     },
                     {
                        "7":{
                           "narrator":"filostrato"
                        }
                     },
                     {
                        "8":{
                           "narrator":"lauretta"
                        }
                     },
                     {
                        "9":{
                           "narrator":"elissa"
                        }
                     },
                     {
                        "10":{
                           "narrator":"pampinea"
                        }
                     },
                     {
                        "conclusion":{
                           "narrator":"author"
                        }
                     }
                  ]
               }
            },
            {
               "2":{
                  "leader":"filomena",
                  "sections":[
                     {
                        "introduction":{
                           "narrator":"author"
                        }
                     },
                     {
                        "1":{
                           "narrator":"neifile"
                        }
                     },
                     {
                        "2":{
                           "narrator":"filostrato"
                        }
                     },
                     {
                        "3":{
                           "narrator":"pampinea"
                        }
                     },
                     {
                        "4":{
                           "narrator":"lauretta"
                        }
                     },
                     {
                        "5":{
                           "narrator":"fiammetta"
                        }
                     },
                     {
                        "6":{
                           "narrator":"emilia"
                        }
                     },
                     {
                        "7":{
                           "narrator":"panfilo"
                        }
                     },
                     {
                        "8":{
                           "narrator":"elissa"
                        }
                     },
                     {
                        "9":{
                           "narrator":"dioneo"
                        }
                     },
                     {
                        "10":{
                           "narrator":"filomena"
                        }
                     },
                     {
                        "conclusion":{
                           "narrator":"author"
                        }
                     }
                  ]
               }
            },
            {
               "3":{
                  "leader":"neifile",
                  "sections":[
                     {
                        "introduction":{
                           "narrator":"author"
                        }
                     },
                     {
                        "1":{
                           "narrator":"filostrato"
                        }
                     },
                     {
                        "2":{
                           "narrator":"pampinea"
                        }
                     },
                     {
                        "3":{
                           "narrator":"filomena"
                        }
                     },
                     {
                        "4":{
                           "narrator":"panfilo"
                        }
                     },
                     {
                        "5":{
                           "narrator":"elissa"
                        }
                     },
                     {
                        "6":{
                           "narrator":"fiammetta"
                        }
                     },
                     {
                        "7":{
                           "narrator":"emilia"
                        }
                     },
                     {
                        "8":{
                           "narrator":"lauretta"
                        }
                     },
                     {
                        "9":{
                           "narrator":"neifile"
                        }
                     },
                     {
                        "10":{
                           "narrator":"dioneo"
                        }
                     },
                     {
                        "conclusion":{
                           "narrator":"author"
                        }
                     }
                  ]
               }
            },
            {
               "4":{
                  "leader":"filostrato",
                  "sections":[
                     {
                        "introduction":{
                           "narrator":"author"
                        }
                     },
                     {
                        "1":{
                           "narrator":"fiammetta"
                        }
                     },
                     {
                        "2":{
                           "narrator":"pampinea"
                        }
                     },
                     {
                        "3":{
                           "narrator":"lauretta"
                        }
                     },
                     {
                        "4":{
                           "narrator":"elissa"
                        }
                     },
                     {
                        "5":{
                           "narrator":"filomena"
                        }
                     },
                     {
                        "6":{
                           "narrator":"panfilo"
                        }
                     },
                     {
                        "7":{
                           "narrator":"emilia"
                        }
                     },
                     {
                        "8":{
                           "narrator":"neifile"
                        }
                     },
                     {
                        "9":{
                           "narrator":"filostrato"
                        }
                     },
                     {
                        "10":{
                           "narrator":"dioneo"
                        }
                     },
                     {
                        "conclusion":{
                           "narrator":"author"
                        }
                     }
                  ]
               }
            },
            {
               "5":{
                  "leader":"fiammetta",
                  "sections":[
                     {
                        "introduction":{
                           "narrator":"author"
                        }
                     },
                     {
                        "1":{
                           "narrator":"panfilo"
                        }
                     },
                     {
                        "2":{
                           "narrator":"emilia"
                        }
                     },
                     {
                        "3":{
                           "narrator":"elissa"
                        }
                     },
                     {
                        "4":{
                           "narrator":"filostrato"
                        }
                     },
                     {
                        "5":{
                           "narrator":"neifile"
                        }
                     },
                     {
                        "6":{
                           "narrator":"pampinea"
                        }
                     },
                     {
                        "7":{
                           "narrator":"lauretta"
                        }
                     },
                     {
                        "8":{
                           "narrator":"filomena"
                        }
                     },
                     {
                        "9":{
                           "narrator":"fiammetta"
                        }
                     },
                     {
                        "10":{
                           "narrator":"dioneo"
                        }
                     },
                     {
                        "conclusion":{
                           "narrator":"author"
                        }
                     }
                  ]
               }
            },
            {
               "6":{
                  "leader":"elissa",
                  "sections":[
                     {
                        "introduction":{
                           "narrator":"author"
                        }
                     },
                     {
                        "1":{
                           "narrator":"filomena"
                        }
                     },
                     {
                        "2":{
                           "narrator":"pampinea"
                        }
                     },
                     {
                        "3":{
                           "narrator":"lauretta"
                        }
                     },
                     {
                        "4":{
                           "narrator":"neifile"
                        }
                     },
                     {
                        "5":{
                           "narrator":"panfilo"
                        }
                     },
                     {
                        "6":{
                           "narrator":"fiammetta"
                        }
                     },
                     {
                        "7":{
                           "narrator":"filostrato"
                        }
                     },
                     {
                        "8":{
                           "narrator":"emilia"
                        }
                     },
                     {
                        "9":{
                           "narrator":"elissa"
                        }
                     },
                     {
                        "10":{
                           "narrator":"dioneo"
                        }
                     },
                     {
                        "conclusion":{
                           "narrator":"author"
                        }
                     }
                  ]
               }
            },
            {
               "7":{
                  "leader":"dioneo",
                  "sections":[
                     {
                        "introduction":{
                           "narrator":"author"
                        }
                     },
                     {
                        "1":{
                           "narrator":"emilia"
                        }
                     },
                     {
                        "2":{
                           "narrator":"filostrato"
                        }
                     },
                     {
                        "3":{
                           "narrator":"elissa"
                        }
                     },
                     {
                        "4":{
                           "narrator":"lauretta"
                        }
                     },
                     {
                        "5":{
                           "narrator":"fiammetta"
                        }
                     },
                     {
                        "6":{
                           "narrator":"pampinea"
                        }
                     },
                     {
                        "7":{
                           "narrator":"filomena"
                        }
                     },
                     {
                        "8":{
                           "narrator":"neifile"
                        }
                     },
                     {
                        "9":{
                           "narrator":"panfilo"
                        }
                     },
                     {
                        "10":{
                           "narrator":"dioneo"
                        }
                     },
                     {
                        "conclusion":{
                           "narrator":"author"
                        }
                     }
                  ]
               }
            },
            {
               "8":{
                  "leader":"lauretta",
                  "sections":[
                     {
                        "introduction":{
                           "narrator":"author"
                        }
                     },
                     {
                        "1":{
                           "narrator":"neifile"
                        }
                     },
                     {
                        "2":{
                           "narrator":"panfilo"
                        }
                     },
                     {
                        "3":{
                           "narrator":"elissa"
                        }
                     },
                     {
                        "4":{
                           "narrator":"emilia"
                        }
                     },
                     {
                        "5":{
                           "narrator":"filostrato"
                        }
                     },
                     {
                        "6":{
                           "narrator":"filomena"
                        }
                     },
                     {
                        "7":{
                           "narrator":"pampinea"
                        }
                     },
                     {
                        "8":{
                           "narrator":"fiammetta"
                        }
                     },
                     {
                        "9":{
                           "narrator":"lauretta"
                        }
                     },
                     {
                        "10":{
                           "narrator":"dioneo"
                        }
                     },
                     {
                        "conclusion":{
                           "narrator":"author"
                        }
                     }
                  ]
               }
            },
            {
               "9":{
                  "leader":"emilia",
                  "sections":[
                     {
                        "introduction":{
                           "narrator":"author"
                        }
                     },
                     {
                        "1":{
                           "narrator":"filomena"
                        }
                     },
                     {
                        "2":{
                           "narrator":"elissa"
                        }
                     },
                     {
                        "3":{
                           "narrator":"filostrato"
                        }
                     },
                     {
                        "4":{
                           "narrator":"neifile"
                        }
                     },
                     {
                        "5":{
                           "narrator":"fiammetta"
                        }
                     },
                     {
                        "6":{
                           "narrator":"panfilo"
                        }
                     },
                     {
                        "7":{
                           "narrator":"pampinea"
                        }
                     },
                     {
                        "8":{
                           "narrator":"lauretta"
                        }
                     },
                     {
                        "9":{
                           "narrator":"emilia"
                        }
                     },
                     {
                        "10":{
                           "narrator":"dioneo"
                        }
                     },
                     {
                        "conclusion":{
                           "narrator":"author"
                        }
                     }
                  ]
               }
            },
            {
               "10":{
                  "leader":"panfilo",
                  "sections":[
                     {
                        "introduction":{
                           "narrator":"author"
                        }
                     },
                     {
                        "1":{
                           "narrator":"neifile"
                        }
                     },
                     {
                        "2":{
                           "narrator":"elissa"
                        }
                     },
                     {
                        "3":{
                           "narrator":"filostrato"
                        }
                     },
                     {
                        "4":{
                           "narrator":"lauretta"
                        }
                     },
                     {
                        "5":{
                           "narrator":"emilia"
                        }
                     },
                     {
                        "6":{
                           "narrator":"fiammetta"
                        }
                     },
                     {
                        "7":{
                           "narrator":"pampinea"
                        }
                     },
                     {
                        "8":{
                           "narrator":"filomena"
                        }
                     },
                     {
                        "9":{
                           "narrator":"panfilo"
                        }
                     },
                     {
                        "10":{
                           "narrator":"dioneo"
                        }
                     },
                     {
                        "conclusion":{
                           "narrator":"author"
                        }
                     }
                  ]
               }
            }
         ]
      },
      {
         "conclusion":{
            "narrator":"author"
         }
      }
   ]
}